Workbook

Sheet Assumptions
A1: NVIDIA Corporation — Key Assumptions & Drivers ($mm) | B1: FY2023 | C1: FY2024 | D1: FY2025 | E1: FY2026E | F1: FY2027E | G1: FY2028E | H1: FY2029E | I1: FY2030E
A3: Revenue Assumptions
A4: Data Center Revenue | B4: 15006 | C4: 47525 | D4: 115190 | E4: 192000 | F4: =E4*(1+F5) -> 278400 | G4: =F4*(1+G5) -> 375840 | H4: =G4*(1+H5) -> 469800 | I4: =H4*(1+I5) -> 554364
A5: Data Center YoY Growth | C5: =(C4-B4)/B4 -> 2.1670665 | D5: =(D4-C4)/C4 -> 1.423777 | E5: 0.667 | F5: 0.45 | G5: 0.35 | H5: 0.25 | I5: 0.18
A7: Gaming Revenue | B7: 10325 | C7: 10445 | D7: 11350 | E7: 16000 | F7: =E7*(1+F8) -> 19200 | G7: =F7*(1+G8) -> 22080 | H7: =G7*(1+H8) -> 24729.6 | I7: =H7*(1+I8) -> 27202.56
A8: Gaming YoY Growth | C8: =(C7-B7)/B7 -> 0.011622276 | D8: =(D7-C7)/C7 -> 0.086644327 | E8: 0.08 | F8: 0.2 | G8: 0.15 | H8: 0.12 | I8: 0.1
A10: Pro Visualization Revenue | B10: 1544 | C10: 1553 | D10: 1690 | E10: 3200 | F10: =E10*(1+F11) -> 3840 | G10: =F10*(1+G11) -> 4608 | H10: =G10*(1+H11) -> 5529.6 | I10: =H10*(1+I11) -> 6635.52
A11: Pro Viz YoY Growth | C11: =(C10-B10)/B10 -> 0.0058290155 | D11: =(D10-C10)/C10 -> 0.088216355 | E11: 0.1 | F11: 0.2 | G11: 0.2 | H11: 0.2 | I11: 0.2
A13: Automotive & Other Revenue | B13: 1099 | C13: 1399 | D13: 2267 | E13: 2300 | F13: =E13*(1+F14) -> 2530 | G13: =F13*(1+G14) -> 2783 | H13: =G13*(1+H14) -> 3061.3 | I13: =H13*(1+I14) -> 3367.43
A14: Auto & Other YoY Growth | C14: =(C13-B13)/B13 -> 0.27297543 | D14: =(D13-C13)/C13 -> 0.62044317 | E14: 0.25 | F14: 0.1 | G14: 0.1 | H14: 0.1 | I14: 0.1
A16: Total Revenue | B16: =B4+B7+B10+B13 -> 27974 | C16: =C4+C7+C10+C13 -> 60922 | D16: =D4+D7+D10+D13 -> 130497 | E16: =E4+E7+E10+E13 -> 213500 | F16: =F4+F7+F10+F13 -> 303970 | G16: =G4+G7+G10+G13 -> 405311 | H16: =H4+H7+H10+H13 -> 503120.5 | I16: =I4+I7+I10+I13 -> 591569.51
A17: Total Revenue Growth | C17: =(C16-B16)/B16 -> 1.177808 | D17: =(D16-C16)/C16 -> 1.1420341 | E17: =(E16-D16)/D16 -> 0.63605294 | F17: =(F16-E16)/E16 -> 0.42374707 | G17: =(G16-F16)/F16 -> 0.33339145 | H17: =(H16-G16)/G16 -> 0.24131963 | I17: =(I16-H16)/H16 -> 0.17580085
A19: Margin & Operating Assumptions
A20: Gross Margin % | B20: 0.5693 | C20: 0.7272 | D20: 0.7499 | E20: 0.74 | F20: 0.73 | G20: 0.72 | H20: 0.71 | I20: 0.7
A21: R&D as % of Revenue | B21: 0.272 | C21: 0.1424 | D21: 0.099 | E21: 0.085 | F21: 0.08 | G21: 0.078 | H21: 0.075 | I21: 0.073
A22: SG&A as % of Revenue | B22: 0.0905 | C22: 0.0436 | D22: 0.0268 | E22: 0.022 | F22: 0.02 | G22: 0.019 | H22: 0.018 | I22: 0.017
A23: D&A ($mm historical / % Rev projected) | B23: 1544 | C23: 1508 | D23: 1864 | E23: 0.012 | F23: 0.012 | G23: 0.011 | H23: 0.011 | I23: 0.01
A25: Tax & Other Assumptions
A26: Effective Tax Rate | B26: -0.0447 | C26: 0.12 | D26: 0.1326 | E26: 0.135 | F26: 0.135 | G26: 0.135 | H26: 0.135 | I26: 0.135
A27: Interest Expense ($mm) | B27: 262 | C27: 257 | D27: 247 | E27: 240 | F27: 230 | G27: 220 | H27: 210 | I27: 200
A28: Interest & Investment Income ($mm) | B28: 267 | C28: 866 | D28: 1786 | E28: 2000 | F28: 2200 | G28: 2400 | H28: 2600 | I28: 2800
A30: Working Capital Assumptions
A31: Days Sales Outstanding (DSO) | B31: 52 | C31: 60 | D31: 65 | E31: 60 | F31: 65 | G31: 64 | H31: 63 | I31: 62
A32: Days Inventory Outstanding (DIO) | B32: 162 | C32: 118 | D32: 113 | E32: 100 | F32: 98 | G32: 95 | H32: 92 | I32: 90
A33: Days Payable Outstanding (DPO) | B33: 37 | C33: 59 | D33: 71 | E33: 65 | F33: 70 | G33: 68 | H33: 67 | I33: 66
A35: CapEx & Debt Schedule
A36: CapEx as % of Revenue | B36: 0.068 | C36: 0.0175 | D36: 0.0248 | E36: 0.03 | F36: 0.03 | G36: 0.028 | H36: 0.026 | I36: 0.025
A37: Long-Term Debt Balance ($mm) | B37: 9703 | C37: 8459 | D37: 8463 | E37: 7469 | F37: 7469 | G37: 7469 | H37: 7469 | I37: 7469
A39: Shares & Buyback Assumptions
A40: Diluted Shares Outstanding (mm) | B40: 25070 | C40: 24940 | D40: 24804 | E40: 24400 | F40: 24000 | G40: 23600 | H40: 23200 | I40: 22800
A42: DCF Assumptions
A43: WACC | B43: 0.09
A44: Terminal Growth Rate | B44: 0.035
A45: Terminal EBITDA Multiple (alt) | B45: 25
A47: Source: NVIDIA 10-K FY2023-FY2025, SEC EDGAR. Projections are illustrative.

Sheet Income Statement
A1: NVIDIA Corporation — Income Statement ($mm) | B1: FY2023 | C1: FY2024 | D1: FY2025 | E1: FY2026E | F1: FY2027E | G1: FY2028E | H1: FY2029E | I1: FY2030E
A3: Revenue by Segment
A4: Data Center | B4: =Assumptions!B4 -> 15006 | C4: =Assumptions!C4 -> 47525 | D4: =Assumptions!D4 -> 115190 | E4: =Assumptions!E4 -> 192000 | F4: =Assumptions!F4 -> 278400 | G4: =Assumptions!G4 -> 375840 | H4: =Assumptions!H4 -> 469800 | I4: =Assumptions!I4 -> 554364
A5: Gaming | B5: =Assumptions!B7 -> 10325 | C5: =Assumptions!C7 -> 10445 | D5: =Assumptions!D7 -> 11350 | E5: =Assumptions!E7 -> 16000 | F5: =Assumptions!F7 -> 19200 | G5: =Assumptions!G7 -> 22080 | H5: =Assumptions!H7 -> 24729.6 | I5: =Assumptions!I7 -> 27202.56
A6: Professional Visualization | B6: =Assumptions!B10 -> 1544 | C6: =Assumptions!C10 -> 1553 | D6: =Assumptions!D10 -> 1690 | E6: =Assumptions!E10 -> 3200 | F6: =Assumptions!F10 -> 3840 | G6: =Assumptions!G10 -> 4608 | H6: =Assumptions!H10 -> 5529.6 | I6: =Assumptions!I10 -> 6635.52
A7: Automotive & Other | B7: =Assumptions!B13 -> 1099 | C7: =Assumptions!C13 -> 1399 | D7: =Assumptions!D13 -> 2267 | E7: =Assumptions!E13 -> 2300 | F7: =Assumptions!F13 -> 2530 | G7: =Assumptions!G13 -> 2783 | H7: =Assumptions!H13 -> 3061.3 | I7: =Assumptions!I13 -> 3367.43
A9: Total Revenue | B9: =B4+B5+B6+B7 -> 27974 | C9: =C4+C5+C6+C7 -> 60922 | D9: =D4+D5+D6+D7 -> 130497 | E9: =E4+E5+E6+E7 -> 213500 | F9: =F4+F5+F6+F7 -> 303970 | G9: =G4+G5+G6+G7 -> 405311 | H9: =H4+H5+H6+H7 -> 503120.5 | I9: =I4+I5+I6+I7 -> 591569.51
A10: Revenue Growth % | C10: =(C9-B9)/B9 -> 1.177808 | D10: =(D9-C9)/C9 -> 1.1420341 | E10: =(E9-D9)/D9 -> 0.63605294 | F10: =(F9-E9)/E9 -> 0.42374707 | G10: =(G9-F9)/F9 -> 0.33339145 | H10: =(H9-G9)/G9 -> 0.24131963 | I10: =(I9-H9)/H9 -> 0.17580085
A12: Cost Structure
A13: Cost of Revenue | B13: =B9*(1-Assumptions!B20) -> 12048.402 | C13: =C9*(1-Assumptions!C20) -> 16619.522 | D13: =D9*(1-Assumptions!D20) -> 32637.3 | E13: =E9*(1-Assumptions!E20) -> 55510 | F13: =F9*(1-Assumptions!F20) -> 82071.9 | G13: =G9*(1-Assumptions!G20) -> 113487.08 | H13: =H9*(1-Assumptions!H20) -> 145904.95 | I13: =I9*(1-Assumptions!I20) -> 177470.85
A15: Gross Profit | B15: =B9-B13 -> 15925.598 | C15: =C9-C13 -> 44302.478 | D15: =D9-D13 -> 97859.7 | E15: =E9-E13 -> 157990 | F15: =F9-F13 -> 221898.1 | G15: =G9-G13 -> 291823.92 | H15: =H9-H13 -> 357215.55 | I15: =I9-I13 -> 414098.66
A16: Gross Margin % | B16: =B15/B9 -> 0.5693 | C16: =C15/C9 -> 0.7272 | D16: =D15/D9 -> 0.7499 | E16: =E15/E9 -> 0.74 | F16: =F15/F9 -> 0.73 | G16: =G15/G9 -> 0.72 | H16: =H15/H9 -> 0.71 | I16: =I15/I9 -> 0.7
A18: Research & Development | B18: =B9*Assumptions!B21 -> 7608.928 | C18: =C9*Assumptions!C21 -> 8675.2928 | D18: =D9*Assumptions!D21 -> 12919.203 | E18: =E9*Assumptions!E21 -> 18147.5 | F18: =F9*Assumptions!F21 -> 24317.6 | G18: =G9*Assumptions!G21 -> 31614.258 | H18: =H9*Assumptions!H21 -> 37734.037 | I18: =I9*Assumptions!I21 -> 43184.574
A19: Selling, General & Administrative | B19: =B9*Assumptions!B22 -> 2531.647 | C19: =C9*Assumptions!C22 -> 2656.1992 | D19: =D9*Assumptions!D22 -> 3497.3196 | E19: =E9*Assumptions!E22 -> 4697 | F19: =F9*Assumptions!F22 -> 6079.4 | G19: =G9*Assumptions!G22 -> 7700.909 | H19: =H9*Assumptions!H22 -> 9056.169 | I19: =I9*Assumptions!I22 -> 10056.682
A20: Depreciation & Amortization | B20: 1544 | C20: 1508 | D20: 1864 | E20: =E9*Assumptions!E23 -> 2562 | F20: =F9*Assumptions!F23 -> 3647.64 | G20: =G9*Assumptions!G23 -> 4458.421 | H20: =H9*Assumptions!H23 -> 5534.3255 | I20: =I9*Assumptions!I23 -> 5915.6951
A22: Total Operating Expenses | B22: =B18+B19+B20 -> 11684.575 | C22: =C18+C19+C20 -> 12839.492 | D22: =D18+D19+D20 -> 18280.523 | E22: =E18+E19+E20 -> 25406.5 | F22: =F18+F19+F20 -> 34044.64 | G22: =G18+G19+G20 -> 43773.588 | H22: =H18+H19+H20 -> 52324.532 | I22: =I18+I19+I20 -> 59156.951
A24: Operating Income (EBIT) | B24: =B15-B22 -> 4241.0232 | C24: =C15-C22 -> 31462.986 | D24: =D15-D22 -> 79579.178 | E24: =E15-E22 -> 132583.5 | F24: =F15-F22 -> 187853.46 | G24: =G15-G22 -> 248050.33 | H24: =H15-H22 -> 304891.02 | I24: =I15-I22 -> 354941.71
A25: Operating Margin % | B25: =B24/B9 -> 0.15160589 | C25: =C24/C9 -> 0.51644704 | D25: =D24/D9 -> 0.60981615 | E25: =E24/E9 -> 0.621 | F25: =F24/F9 -> 0.618 | G25: =G24/G9 -> 0.612 | H25: =H24/H9 -> 0.606 | I25: =I24/I9 -> 0.6
A27: Below the Line
A28: Interest Expense | B28: =-Assumptions!B27 -> -262 | C28: =-Assumptions!C27 -> -257 | D28: =-Assumptions!D27 -> -247 | E28: =-Assumptions!E27 -> -240 | F28: =-Assumptions!F27 -> -230 | G28: =-Assumptions!G27 -> -220 | H28: =-Assumptions!H27 -> -210 | I28: =-Assumptions!I27 -> -200
A29: Interest & Investment Income | B29: =Assumptions!B28 -> 267 | C29: =Assumptions!C28 -> 866 | D29: =Assumptions!D28 -> 1786 | E29: =Assumptions!E28 -> 2000 | F29: =Assumptions!F28 -> 2200 | G29: =Assumptions!G28 -> 2400 | H29: =Assumptions!H28 -> 2600 | I29: =Assumptions!I28 -> 2800
A31: Pretax Income (EBT) | B31: =B24+B28+B29 -> 4246.0232 | C31: =C24+C28+C29 -> 32071.986 | D31: =D24+D28+D29 -> 81118.178 | E31: =E24+E28+E29 -> 134343.5 | F31: =F24+F28+F29 -> 189823.46 | G31: =G24+G28+G29 -> 250230.33 | H31: =H24+H28+H29 -> 307281.02 | I31: =I24+I28+I29 -> 357541.71
A32: Income Tax Expense | B32: =B31*Assumptions!B26 -> -189.79724 | C32: =C31*Assumptions!C26 -> 3848.6384 | D32: =D31*Assumptions!D26 -> 10756.27 | E32: =E31*Assumptions!E26 -> 18136.373 | F32: =F31*Assumptions!F26 -> 25626.167 | G32: =G31*Assumptions!G26 -> 33781.095 | H32: =H31*Assumptions!H26 -> 41482.938 | I32: =I31*Assumptions!I26 -> 48268.13
A34: Net Income | B34: =B31-B32 -> 4435.8204 | C34: =C31-C32 -> 28223.348 | D34: =D31-D32 -> 70361.907 | E34: =E31-E32 -> 116207.13 | F34: =F31-F32 -> 164197.29 | G34: =G31-G32 -> 216449.24 | H34: =H31-H32 -> 265798.08 | I34: =I31-I32 -> 309273.58
A35: Net Margin % | B35: =B34/B9 -> 0.1585694 | C35: =C34/C9 -> 0.46327021 | D35: =D34/D9 -> 0.5391841 | E35: =E34/E9 -> 0.54429568 | F35: =F34/F9 -> 0.54017598 | G35: =G34/G9 -> 0.53403248 | H35: =H34/H9 -> 0.52829906 | I35: =I34/I9 -> 0.52280175
A37: EBITDA | B37: =B24+B20 -> 5785.0232 | C37: =C24+C20 -> 32970.986 | D37: =D24+D20 -> 81443.178 | E37: =E24+E20 -> 135145.5 | F37: =F24+F20 -> 191501.1 | G37: =G24+G20 -> 252508.75 | H37: =H24+H20 -> 310425.35 | I37: =I24+I20 -> 360857.4
A38: EBITDA Margin % | B38: =B37/B9 -> 0.2068 | C38: =C37/C9 -> 0.5412 | D38: =D37/D9 -> 0.6241 | E38: =E37/E9 -> 0.633 | F38: =F37/F9 -> 0.63 | G38: =G37/G9 -> 0.623 | H38: =H37/H9 -> 0.617 | I38: =I37/I9 -> 0.61
A40: Diluted EPS | B40: =B34/Assumptions!B40 -> 0.17693739 | C40: =C34/Assumptions!C40 -> 1.1316499 | D40: =D34/Assumptions!D40 -> 2.8367161 | E40: =E34/Assumptions!E40 -> 4.7625872 | F40: =F34/Assumptions!F40 -> 6.8415539 | G40: =G34/Assumptions!G40 -> 9.1715778 | H40: =H34/Assumptions!H40 -> 11.456814 | I40: =I34/Assumptions!I40 -> 13.564631
A41: Diluted Shares (mm) | B41: =Assumptions!B40 -> 25070 | C41: =Assumptions!C40 -> 24940 | D41: =Assumptions!D40 -> 24804 | E41: =Assumptions!E40 -> 24400 | F41: =Assumptions!F40 -> 24000 | G41: =Assumptions!G40 -> 23600 | H41: =Assumptions!H40 -> 23200 | I41: =Assumptions!I40 -> 22800

Sheet Balance Sheet
A1: NVIDIA Corporation — Balance Sheet ($mm) | B1: FY2023 | C1: FY2024 | D1: FY2025 | E1: FY2026E | F1: FY2027E | G1: FY2028E | H1: FY2029E | I1: FY2030E
A3: Current Assets
A4: Cash & Equivalents | B4: 3389 | C4: 7280 | D4: 8589 | E4: ='Cash Flow'!E35 -> 65216.91 | F4: ='Cash Flow'!F35 -> 162598.62 | G4: ='Cash Flow'!G35 -> 312726.36 | H4: ='Cash Flow'!H35 -> 514292.38 | I4: ='Cash Flow'!I35 -> 761298.58
A5: Short-Term Investments | B5: 9907 | C5: 18704 | D5: 34621 | E5: 34621 | F5: 34621 | G5: 34621 | H5: 34621 | I5: 34621
A6: Accounts Receivable | B6: 3827 | C6: 9999 | D6: 23065 | E6: ='Income Statement'!E9*Assumptions!E31/365 -> 35095.89 | F6: ='Income Statement'!F9*Assumptions!F31/365 -> 54131.644 | G6: ='Income Statement'!G9*Assumptions!G31/365 -> 71068.23 | H6: ='Income Statement'!H9*Assumptions!H31/365 -> 86839.977 | I6: ='Income Statement'!I9*Assumptions!I31/365 -> 100485.78
A7: Inventory | B7: 5159 | C7: 5282 | D7: 10080 | E7: ='Income Statement'!E13*Assumptions!E32/365 -> 15208.219 | F7: ='Income Statement'!F13*Assumptions!F32/365 -> 22035.743 | G7: ='Income Statement'!G13*Assumptions!G32/365 -> 29537.733 | H7: ='Income Statement'!H13*Assumptions!H32/365 -> 36776.041 | I7: ='Income Statement'!I13*Assumptions!I32/365 -> 43759.936
A8: Other Current Assets | B8: 791 | C8: 3080 | D8: 3771 | E8: =D8*1.05 -> 3959.55 | F8: =E8*1.05 -> 4157.5275 | G8: =F8*1.05 -> 4365.4039 | H8: =G8*1.05 -> 4583.6741 | I8: =H8*1.05 -> 4812.8578
A10: Total Current Assets | B10: =SUM(B4:B8) -> 23073 | C10: =SUM(C4:C8) -> 44345 | D10: =SUM(D4:D8) -> 80126 | E10: =SUM(E4:E8) -> 154101.57 | F10: =SUM(F4:F8) -> 277544.54 | G10: =SUM(G4:G8) -> 452318.73 | H10: =SUM(H4:H8) -> 677113.07 | I10: =SUM(I4:I8) -> 944978.16
A12: Non-Current Assets
A13: Net PP&E | B13: 4845 | C13: 5260 | D13: 8076 | E13: =D13+'Income Statement'!E9*Assumptions!E36-'Income Statement'!E20 -> 11919 | F13: =E13+'Income Statement'!F9*Assumptions!F36-'Income Statement'!F20 -> 17390.46 | G13: =F13+'Income Statement'!G9*Assumptions!G36-'Income Statement'!G20 -> 24280.747 | H13: =G13+'Income Statement'!H9*Assumptions!H36-'Income Statement'!H20 -> 31827.554 | I13: =H13+'Income Statement'!I9*Assumptions!I36-'Income Statement'!I20 -> 40701.097
A14: Goodwill & Intangibles | B14: 6048 | C14: 5542 | D14: 5995 | E14: =D14 -> 5995 | F14: =E14 -> 5995 | G14: =F14 -> 5995 | H14: =G14 -> 5995 | I14: =H14 -> 5995
A15: Other Non-Current Assets | B15: 7216 | C15: 10581 | D15: 17404 | E15: =E39-E10-E13-E14 -> 19020.61 | F15: =F39-F10-F13-F14 -> 21739.319 | G15: =G39-G10-G13-G14 -> 24544.386 | H15: =H39-H10-H13-H14 -> 27442.563 | I15: =I39-I10-I13-I14 -> 30441.133
A17: TOTAL ASSETS | B17: =B10+B13+B14+B15 -> 41182 | C17: =C10+C13+C14+C15 -> 65728 | D17: =D10+D13+D14+D15 -> 111601 | E17: =E10+E13+E14+E15 -> 191036.18 | F17: =F10+F13+F14+F15 -> 322669.32 | G17: =G10+G13+G14+G15 -> 507138.86 | H17: =H10+H13+H14+H15 -> 742378.19 | I17: =I10+I13+I14+I15 -> 1022115.4
A19: Current Liabilities
A20: Accounts Payable | B20: 1193 | C20: 2699 | D20: 6310 | E20: ='Income Statement'!E13*Assumptions!E33/365 -> 9885.3425 | F20: ='Income Statement'!F13*Assumptions!F33/365 -> 15739.816 | G20: ='Income Statement'!G13*Assumptions!G33/365 -> 21142.798 | H20: ='Income Statement'!H13*Assumptions!H33/365 -> 26782.552 | I20: ='Income Statement'!I13*Assumptions!I33/365 -> 32090.62
A21: Accrued & Other Current Liabilities | B21: 5370 | C21: 7931 | D21: 11737 | E21: =D21*1.08 -> 12675.96 | F21: =E21*1.08 -> 13690.037 | G21: =F21*1.08 -> 14785.24 | H21: =G21*1.08 -> 15968.059 | I21: =H21*1.08 -> 17245.504
A22: Short-Term Debt | B22: 1250 | C22: 1250 | D22: 0 | E22: 0 | F22: 0 | G22: 0 | H22: 0 | I22: 0
A24: Total Current Liabilities | B24: =B20+B21+B22 -> 7813 | C24: =C20+C21+C22 -> 11880 | D24: =D20+D21+D22 -> 18047 | E24: =E20+E21+E22 -> 22561.302 | F24: =F20+F21+F22 -> 29429.853 | G24: =G20+G21+G22 -> 35928.038 | H24: =H20+H21+H22 -> 42750.61 | I24: =I20+I21+I22 -> 49336.124
A26: Non-Current Liabilities
A27: Long-Term Debt | B27: =Assumptions!B37 -> 9703 | C27: =Assumptions!C37 -> 8459 | D27: =Assumptions!D37 -> 8463 | E27: =Assumptions!E37 -> 7469 | F27: =Assumptions!F37 -> 7469 | G27: =Assumptions!G37 -> 7469 | H27: =Assumptions!H37 -> 7469 | I27: =Assumptions!I37 -> 7469
A28: Other LT Liabilities | B28: 2815 | C28: 3660 | D28: 5764 | E28: =D28*1.05 -> 6052.2 | F28: =E28*1.05 -> 6354.81 | G28: =F28*1.05 -> 6672.5505 | H28: =G28*1.05 -> 7006.178 | I28: =H28*1.05 -> 7356.4869
A30: TOTAL LIABILITIES | B30: =B24+B27+B28 -> 20331 | C30: =C24+C27+C28 -> 23999 | D30: =D24+D27+D28 -> 32274 | E30: =E24+E27+E28 -> 36082.502 | F30: =F24+F27+F28 -> 43253.663 | G30: =G24+G27+G28 -> 50069.589 | H30: =H24+H27+H28 -> 57225.788 | I30: =I24+I27+I28 -> 64161.611
A32: Shareholders' Equity
A33: Common Stock & APIC | B33: 11973 | C33: 13134 | D33: 11261 | E33: =D33+'Cash Flow'!E6 -> 16708.55 | F33: =E33+'Cash Flow'!F6 -> 22973.232 | G33: =F33+'Cash Flow'!G6 -> 30177.617 | H33: =G33+'Cash Flow'!H6 -> 38462.66 | I33: =H33+'Cash Flow'!I6 -> 47990.459
A34: Retained Earnings | B34: 10171 | C34: 29817 | D34: 68038 | E34: =D34+'Income Statement'!E34+'Cash Flow'!E24+'Cash Flow'!E25 -> 138245.13 | F34: =E34+'Income Statement'!F34+'Cash Flow'!F24+'Cash Flow'!F25 -> 256442.42 | G34: =F34+'Income Statement'!G34+'Cash Flow'!G24+'Cash Flow'!G25 -> 426891.66 | H34: =G34+'Income Statement'!H34+'Cash Flow'!H24+'Cash Flow'!H25 -> 646689.74 | I34: =H34+'Income Statement'!I34+'Cash Flow'!I24+'Cash Flow'!I25 -> 909963.32
A35: AOCI & Other | B35: -43 | C35: 27 | D35: 28 | E35: 0 | F35: 0 | G35: 0 | H35: 0 | I35: 0
A37: TOTAL SHAREHOLDERS' EQUITY | B37: =B33+B34+B35 -> 22101 | C37: =C33+C34+C35 -> 42978 | D37: =D33+D34+D35 -> 79327 | E37: =E33+E34+E35 -> 154953.68 | F37: =F33+F34+F35 -> 279415.65 | G37: =G33+G34+G35 -> 457069.27 | H37: =H33+H34+H35 -> 685152.4 | I37: =I33+I34+I35 -> 957953.78
A39: TOTAL LIABILITIES & EQUITY | B39: =B30+B37 -> 42432 | C39: =C30+C37 -> 66977 | D39: =D30+D37 -> 111601 | E39: =E30+E37 -> 191036.18 | F39: =F30+F37 -> 322669.32 | G39: =G30+G37 -> 507138.86 | H39: =H30+H37 -> 742378.19 | I39: =I30+I37 -> 1022115.4
A41: Balance Check (Assets - L&E) | B41: =B17-B39 -> -1250 | C41: =C17-C39 -> -1249 | D41: =D17-D39 -> 0 | E41: =E17-E39 -> 0 | F41: =F17-F39 -> 0 | G41: =G17-G39 -> 0 | H41: =H17-H39 -> 0 | I41: =I17-I39 -> 0

Sheet Cash Flow
A1: NVIDIA Corporation — Cash Flow Statement ($mm) | B1: FY2023 | C1: FY2024 | D1: FY2025 | E1: FY2026E | F1: FY2027E | G1: FY2028E | H1: FY2029E | I1: FY2030E
A3: Cash Flow from Operations
A4: Net Income | B4: ='Income Statement'!B34 -> 4435.8204 | C4: ='Income Statement'!C34 -> 28223.348 | D4: ='Income Statement'!D34 -> 70361.907 | E4: ='Income Statement'!E34 -> 116207.13 | F4: ='Income Statement'!F34 -> 164197.29 | G4: ='Income Statement'!G34 -> 216449.24 | H4: ='Income Statement'!H34 -> 265798.08 | I4: ='Income Statement'!I34 -> 309273.58
A5: (+) Depreciation & Amortization | B5: ='Income Statement'!B20 -> 1544 | C5: ='Income Statement'!C20 -> 1508 | D5: ='Income Statement'!D20 -> 1864 | E5: ='Income Statement'!E20 -> 2562 | F5: ='Income Statement'!F20 -> 3647.64 | G5: ='Income Statement'!G20 -> 4458.421 | H5: ='Income Statement'!H20 -> 5534.3255 | I5: ='Income Statement'!I20 -> 5915.6951
A6: (+) Stock-Based Compensation | B6: 2709 | C6: 3549 | D6: 4737 | E6: =D6*1.15 -> 5447.55 | F6: =E6*1.15 -> 6264.6825 | G6: =F6*1.15 -> 7204.3849 | H6: =G6*1.15 -> 8285.0426 | I6: =H6*1.15 -> 9527.799
A8: Changes in Working Capital:
A9: (Inc)/Dec in Accounts Receivable | B9: 822 | C9: -6172 | D9: -13063 | E9: ='Balance Sheet'!D6-'Balance Sheet'!E6 -> -12030.89 | F9: ='Balance Sheet'!E6-'Balance Sheet'!F6 -> -19035.753 | G9: ='Balance Sheet'!F6-'Balance Sheet'!G6 -> -16936.586 | H9: ='Balance Sheet'!G6-'Balance Sheet'!H6 -> -15771.747 | I9: ='Balance Sheet'!H6-'Balance Sheet'!I6 -> -13645.803
A10: (Inc)/Dec in Inventory | B10: -2554 | C10: -98 | D10: -4781 | E10: ='Balance Sheet'!D7-'Balance Sheet'!E7 -> -5128.2192 | F10: ='Balance Sheet'!E7-'Balance Sheet'!F7 -> -6827.5238 | G10: ='Balance Sheet'!F7-'Balance Sheet'!G7 -> -7501.9901 | H10: ='Balance Sheet'!G7-'Balance Sheet'!H7 -> -7238.3078 | I10: ='Balance Sheet'!H7-'Balance Sheet'!I7 -> -6983.8954
A11: Inc/(Dec) in Accounts Payable | B11: -551 | C11: 1531 | D11: 3357 | E11: ='Balance Sheet'!E20-'Balance Sheet'!D20 -> 3575.3425 | F11: ='Balance Sheet'!F20-'Balance Sheet'!E20 -> 5854.474 | G11: ='Balance Sheet'!G20-'Balance Sheet'!F20 -> 5402.982 | H11: ='Balance Sheet'!H20-'Balance Sheet'!G20 -> 5639.7531 | I11: ='Balance Sheet'!I20-'Balance Sheet'!H20 -> 5308.0684
A12: Other Working Capital Changes | B12: -742 | C12: -983 | D12: 125 | E12: 0 | F12: 0 | G12: 0 | H12: 0 | I12: 0
A14: Cash from Operations (CFO) | B14: =B4+B5+B6+B9+B10+B11+B12 -> 5663.8204 | C14: =C4+C5+C6+C9+C10+C11+C12 -> 27558.348 | D14: =D4+D5+D6+D9+D10+D11+D12 -> 62600.907 | E14: =E4+E5+E6+E9+E10+E11+E12 -> 110632.91 | F14: =F4+F5+F6+F9+F10+F11+F12 -> 154100.81 | G14: =G4+G5+G6+G9+G10+G11+G12 -> 209076.45 | H14: =H4+H5+H6+H9+H10+H11+H12 -> 262247.15 | I14: =I4+I5+I6+I9+I10+I11+I12 -> 309395.44
A16: Cash Flow from Investing
A17: Capital Expenditures | B17: -1833 | C17: -1069 | D17: -3236 | E17: =-'Income Statement'!E9*Assumptions!E36 -> -6405 | F17: =-'Income Statement'!F9*Assumptions!F36 -> -9119.1 | G17: =-'Income Statement'!G9*Assumptions!G36 -> -11348.708 | H17: =-'Income Statement'!H9*Assumptions!H36 -> -13081.133 | I17: =-'Income Statement'!I9*Assumptions!I36 -> -14789.238
A18: Acquisitions & Other Investing | B18: -49 | C18: -9497 | D18: -17207 | E18: -2000 | F18: -2000 | G18: -2000 | H18: -2000 | I18: -2000
A20: Cash from Investing (CFI) | B20: =B17+B18 -> -1882 | C20: =C17+C18 -> -10566 | D20: =D17+D18 -> -20443 | E20: =E17+E18 -> -8405 | F20: =F17+F18 -> -11119.1 | G20: =G17+G18 -> -13348.708 | H20: =H17+H18 -> -15081.133 | I20: =I17+I18 -> -16789.238
A22: Cash Flow from Financing
A23: Debt Issuance / (Repayment) | B23: 0 | C23: -1250 | D23: -1250 | E23: 0 | F23: 0 | G23: 0 | H23: 0 | I23: 0
A24: Share Repurchases | B24: -11514 | C24: -12316 | D24: -40636 | E24: -45000 | F24: -45000 | G24: -45000 | H24: -45000 | I24: -45000
A25: Dividends Paid | B25: -398 | C25: -395 | D25: -834 | E25: -1000 | F25: -1000 | G25: -1000 | H25: -1000 | I25: -1000
A26: Other Financing | B26: 295 | C26: 328 | D26: 361 | E26: 400 | F26: 400 | G26: 400 | H26: 400 | I26: 400
A28: Cash from Financing (CFF) | B28: =B23+B24+B25+B26 -> -11617 | C28: =C23+C24+C25+C26 -> -13633 | D28: =D23+D24+D25+D26 -> -42359 | E28: =E23+E24+E25+E26 -> -45600 | F28: =F23+F24+F25+F26 -> -45600 | G28: =G23+G24+G25+G26 -> -45600 | H28: =H23+H24+H25+H26 -> -45600 | I28: =I23+I24+I25+I26 -> -45600
A30: Cash Summary
A31: Net Change in Cash | B31: =B14+B20+B28 -> -7835.1796 | C31: =C14+C20+C28 -> 3359.348 | D31: =D14+D20+D28 -> -201.09266 | E31: =E14+E20+E28 -> 56627.91 | F31: =F14+F20+F28 -> 97381.712 | G31: =G14+G20+G28 -> 150127.74 | H31: =H14+H20+H28 -> 201566.02 | I31: =I14+I20+I28 -> 247006.2
A33: Beginning Cash Balance | B33: 1990 | C33: 3389 | D33: 7280 | E33: ='Balance Sheet'!D4 -> 8589 | F33: =E35 -> 65216.91 | G33: =F35 -> 162598.62 | H33: =G35 -> 312726.36 | I33: =H35 -> 514292.38
A35: Ending Cash Balance | B35: =B33+B31 -> -5845.1796 | C35: =C33+C31 -> 6748.348 | D35: =D33+D31 -> 7078.9073 | E35: =E33+E31 -> 65216.91 | F35: =F33+F31 -> 162598.62 | G35: =G33+G31 -> 312726.36 | H35: =H33+H31 -> 514292.38 | I35: =I33+I31 -> 761298.58
A37: Free Cash Flow (CFO - CapEx) | B37: =B14+B17 -> 3830.8204 | C37: =C14+C17 -> 26489.348 | D37: =D14+D17 -> 59364.907 | E37: =E14+E17 -> 104227.91 | F37: =F14+F17 -> 144981.71 | G37: =G14+G17 -> 197727.74 | H37: =H14+H17 -> 249166.02 | I37: =I14+I17 -> 294606.2
A38: FCF Margin % | B38: =B37/'Income Statement'!B9 -> 0.13694218 | C38: =C37/'Income Statement'!C9 -> 0.43480759 | D38: =D37/'Income Statement'!D9 -> 0.45491396 | E38: =E37/'Income Statement'!E9 -> 0.48818693 | F38: =F37/'Income Statement'!F9 -> 0.4769606 | G38: =G37/'Income Statement'!G9 -> 0.48784203 | H38: =H37/'Income Statement'!H9 -> 0.49524124 | I38: =I37/'Income Statement'!I9 -> 0.49800775

Sheet DCF Valuation
A1: NVIDIA Corporation — DCF Valuation ($mm) | B1: FY2023 | C1: FY2024 | D1: FY2025 | E1: FY2026E | F1: FY2027E | G1: FY2028E | H1: FY2029E | I1: FY2030E
A3: Unlevered Free Cash Flow Projection
A4: EBITDA | E4: ='Income Statement'!E37 -> 135145.5 | F4: ='Income Statement'!F37 -> 191501.1 | G4: ='Income Statement'!G37 -> 252508.75 | H4: ='Income Statement'!H37 -> 310425.35 | I4: ='Income Statement'!I37 -> 360857.4
A5: (-) Taxes on EBIT | E5: =-'Income Statement'!E24*Assumptions!E26 -> -17898.773 | F5: =-'Income Statement'!F24*Assumptions!F26 -> -25360.217 | G5: =-'Income Statement'!G24*Assumptions!G26 -> -33486.795 | H5: =-'Income Statement'!H24*Assumptions!H26 -> -41160.288 | I5: =-'Income Statement'!I24*Assumptions!I26 -> -47917.13
A6: (+) D&A (already in EBITDA) | E6: 0 | F6: 0 | G6: 0 | H6: 0 | I6: 0
A7: (-) CapEx | E7: ='Cash Flow'!E17 -> -6405 | F7: ='Cash Flow'!F17 -> -9119.1 | G7: ='Cash Flow'!G17 -> -11348.708 | H7: ='Cash Flow'!H17 -> -13081.133 | I7: ='Cash Flow'!I17 -> -14789.238
A8: (-) Change in NWC | E8: ='Cash Flow'!E9+'Cash Flow'!E10+'Cash Flow'!E11 -> -13583.767 | F8: ='Cash Flow'!F9+'Cash Flow'!F10+'Cash Flow'!F11 -> -20008.803 | G8: ='Cash Flow'!G9+'Cash Flow'!G10+'Cash Flow'!G11 -> -19035.594 | H8: ='Cash Flow'!H9+'Cash Flow'!H10+'Cash Flow'!H11 -> -17370.301 | I8: ='Cash Flow'!I9+'Cash Flow'!I10+'Cash Flow'!I11 -> -15321.63
A10: Unlevered Free Cash Flow (UFCF) | E10: =E4+E5+E6+E7+E8 -> 97257.96 | F10: =F4+F5+F6+F7+F8 -> 137012.98 | G10: =G4+G5+G6+G7+G8 -> 188637.66 | H10: =H4+H5+H6+H7+H8 -> 238813.63 | I10: =I4+I5+I6+I7+I8 -> 282829.4
A12: Discounting
A13: WACC | B13: =Assumptions!B43 -> 0.09
A14: Discount Period | E14: 1 | F14: 2 | G14: 3 | H14: 4 | I14: 5
A15: Discount Factor | E15: =1/(1+$B$13)^E14 -> 0.91743119 | F15: =1/(1+$B$13)^F14 -> 0.84167999 | G15: =1/(1+$B$13)^G14 -> 0.77218348 | H15: =1/(1+$B$13)^H14 -> 0.70842521 | I15: =1/(1+$B$13)^I14 -> 0.64993139
A16: PV of UFCF | E16: =E10*E15 -> 89227.487 | F16: =F10*F15 -> 115321.08 | G16: =G10*G15 -> 145662.88 | H16: =H10*H15 -> 169181.59 | I16: =I10*I15 -> 183819.71
A18: Terminal Value
A19: Terminal Growth Rate | B19: =Assumptions!B44 -> 0.035
A20: Gordon Growth TV | B20: =I10*(1+B19)/(B13-B19) -> 5322335.1
A21: PV of Terminal Value | B21: =B20*I15 -> 3459152.6
A22: Exit Multiple TV (alt) | B22: ='Income Statement'!I37*Assumptions!B45 -> 9021435
A23: PV of Exit Multiple TV | B23: =B22*I15 -> 5863313.8
A25: Enterprise & Equity Value
A26: Sum of PV of UFCFs | B26: =SUM(E16:I16) -> 703212.75
A27: (+) PV of Terminal Value (Gordon Growth) | B27: =B21 -> 3459152.6
A28: Enterprise Value (Gordon Growth) | B28: =B26+B27 -> 4162365.4
A29: Enterprise Value (Exit Multiple) | B29: =B26+B23 -> 6566526.5
A31: (-) Total Debt (FY2025) | B31: =-'Balance Sheet'!D27-'Balance Sheet'!D22 -> -8463
A32: (+) Cash & ST Investments (FY2025) | B32: ='Balance Sheet'!D4+'Balance Sheet'!D5 -> 43210
A34: Equity Value (Gordon Growth) | B34: =B28+B31+B32 -> 4197112.4
A35: Equity Value (Exit Multiple) | B35: =B29+B31+B32 -> 6601273.5
A37: Diluted Shares (mm, FY2025) | B37: =Assumptions!D40 -> 24804
A39: Implied Share Price (Gordon Growth) | B39: =B34/B37 -> 169.21111
A40: Implied Share Price (Exit Multiple) | B40: =B35/B37 -> 266.13746

Sheet Scenarios
A1: NVIDIA Corporation — Scenario / Sensitivity Analysis | B1: FY2023 | C1: FY2024 | D1: FY2025 | E1: FY2026E | F1: FY2027E | G1: FY2028E | H1: FY2029E | I1: FY2030E
A3: WACC vs Terminal Growth Rate — Implied Share Price
A4: WACC ↓ / g → | B4: 0.02 | C4: 0.025 | D4: 0.03 | E4: 0.035 | F4: 0.04
A5: 0.08 | B5: =('DCF Valuation'!B26 + 'DCF Valuation'!I10*(1+B$4)/($A$5-B$4)/(1+$A$5)^5 + 'DCF Valuation'!B31 + 'DCF Valuation'!B32) / 'DCF Valuation'!B37 -> 161.67843 | C5: =('DCF Valuation'!B26 + 'DCF Valuation'!I10*(1+C$4)/($A$5-C$4)/(1+$A$5)^5 + 'DCF Valuation'!B31 + 'DCF Valuation'!B32) / 'DCF Valuation'!B37 -> 174.37726 | D5: =('DCF Valuation'!B26 + 'DCF Valuation'!I10*(1+D$4)/($A$5-D$4)/(1+$A$5)^5 + 'DCF Valuation'!B31 + 'DCF Valuation'!B32) / 'DCF Valuation'!B37 -> 189.61586 | E5: =('DCF Valuation'!B26 + 'DCF Valuation'!I10*(1+E$4)/($A$5-E$4)/(1+$A$5)^5 + 'DCF Valuation'!B31 + 'DCF Valuation'!B32) / 'DCF Valuation'!B37 -> 208.24082 | F5: =('DCF Valuation'!B26 + 'DCF Valuation'!I10*(1+F$4)/($A$5-F$4)/(1+$A$5)^5 + 'DCF Valuation'!B31 + 'DCF Valuation'!B32) / 'DCF Valuation'!B37 -> 231.52202
A6: 0.09 | B6: =('DCF Valuation'!B26 + 'DCF Valuation'!I10*(1+B$4)/($A$6-B$4)/(1+$A$6)^5 + 'DCF Valuation'!B31 + 'DCF Valuation'!B32) / 'DCF Valuation'!B37 -> 137.73889 | C6: =('DCF Valuation'!B26 + 'DCF Valuation'!I10*(1+C$4)/($A$6-C$4)/(1+$A$6)^5 + 'DCF Valuation'!B31 + 'DCF Valuation'!B32) / 'DCF Valuation'!B37 -> 146.61567 | D6: =('DCF Valuation'!B26 + 'DCF Valuation'!I10*(1+D$4)/($A$6-D$4)/(1+$A$6)^5 + 'DCF Valuation'!B31 + 'DCF Valuation'!B32) / 'DCF Valuation'!B37 -> 156.97191 | E6: =('DCF Valuation'!B26 + 'DCF Valuation'!I10*(1+E$4)/($A$6-E$4)/(1+$A$6)^5 + 'DCF Valuation'!B31 + 'DCF Valuation'!B32) / 'DCF Valuation'!B37 -> 169.21111 | F6: =('DCF Valuation'!B26 + 'DCF Valuation'!I10*(1+F$4)/($A$6-F$4)/(1+$A$6)^5 + 'DCF Valuation'!B31 + 'DCF Valuation'!B32) / 'DCF Valuation'!B37 -> 183.89815
A7: 0.1 | B7: =('DCF Valuation'!B26 + 'DCF Valuation'!I10*(1+B$4)/($A$7-B$4)/(1+$A$7)^5 + 'DCF Valuation'!B31 + 'DCF Valuation'!B32) / 'DCF Valuation'!B37 -> 120.02292 | C7: =('DCF Valuation'!B26 + 'DCF Valuation'!I10*(1+C$4)/($A$7-C$4)/(1+$A$7)^5 + 'DCF Valuation'!B31 + 'DCF Valuation'!B32) / 'DCF Valuation'!B37 -> 126.51301 | D7: =('DCF Valuation'!B26 + 'DCF Valuation'!I10*(1+D$4)/($A$7-D$4)/(1+$A$7)^5 + 'DCF Valuation'!B31 + 'DCF Valuation'!B32) / 'DCF Valuation'!B37 -> 133.93026 | E7: =('DCF Valuation'!B26 + 'DCF Valuation'!I10*(1+E$4)/($A$7-E$4)/(1+$A$7)^5 + 'DCF Valuation'!B31 + 'DCF Valuation'!B32) / 'DCF Valuation'!B37 -> 142.48862 | F7: =('DCF Valuation'!B26 + 'DCF Valuation'!I10*(1+F$4)/($A$7-F$4)/(1+$A$7)^5 + 'DCF Valuation'!B31 + 'DCF Valuation'!B32) / 'DCF Valuation'!B37 -> 152.47338
A8: 0.11 | B8: =('DCF Valuation'!B26 + 'DCF Valuation'!I10*(1+B$4)/($A$8-B$4)/(1+$A$8)^5 + 'DCF Valuation'!B31 + 'DCF Valuation'!B32) / 'DCF Valuation'!B37 -> 106.44286 | C8: =('DCF Valuation'!B26 + 'DCF Valuation'!I10*(1+C$4)/($A$8-C$4)/(1+$A$8)^5 + 'DCF Valuation'!B31 + 'DCF Valuation'!B32) / 'DCF Valuation'!B37 -> 111.35215 | D8: =('DCF Valuation'!B26 + 'DCF Valuation'!I10*(1+D$4)/($A$8-D$4)/(1+$A$8)^5 + 'DCF Valuation'!B31 + 'DCF Valuation'!B32) / 'DCF Valuation'!B37 -> 116.87512 | E8: =('DCF Valuation'!B26 + 'DCF Valuation'!I10*(1+E$4)/($A$8-E$4)/(1+$A$8)^5 + 'DCF Valuation'!B31 + 'DCF Valuation'!B32) / 'DCF Valuation'!B37 -> 123.13447 | F8: =('DCF Valuation'!B26 + 'DCF Valuation'!I10*(1+F$4)/($A$8-F$4)/(1+$A$8)^5 + 'DCF Valuation'!B31 + 'DCF Valuation'!B32) / 'DCF Valuation'!B37 -> 130.28802
A9: 0.12 | B9: =('DCF Valuation'!B26 + 'DCF Valuation'!I10*(1+B$4)/($A$9-B$4)/(1+$A$9)^5 + 'DCF Valuation'!B31 + 'DCF Valuation'!B32) / 'DCF Valuation'!B37 -> 95.746925 | C9: =('DCF Valuation'!B26 + 'DCF Valuation'!I10*(1+C$4)/($A$9-C$4)/(1+$A$9)^5 + 'DCF Valuation'!B31 + 'DCF Valuation'!B32) / 'DCF Valuation'!B37 -> 99.560894 | D9: =('DCF Valuation'!B26 + 'DCF Valuation'!I10*(1+D$4)/($A$9-D$4)/(1+$A$9)^5 + 'DCF Valuation'!B31 + 'DCF Valuation'!B32) / 'DCF Valuation'!B37 -> 103.79864 | E9: =('DCF Valuation'!B26 + 'DCF Valuation'!I10*(1+E$4)/($A$9-E$4)/(1+$A$9)^5 + 'DCF Valuation'!B31 + 'DCF Valuation'!B32) / 'DCF Valuation'!B37 -> 108.53494 | F9: =('DCF Valuation'!B26 + 'DCF Valuation'!I10*(1+F$4)/($A$9-F$4)/(1+$A$9)^5 + 'DCF Valuation'!B31 + 'DCF Valuation'!B32) / 'DCF Valuation'!B37 -> 113.86328
A12: WACC vs Terminal EBITDA Multiple — Implied Share Price
A13: WACC ↓ / Multiple → | B13: 20 | C13: 22.5 | D13: 25 | E13: 27.5 | F13: 30
A14: 0.08 | B14: =('DCF Valuation'!B26 + 'Income Statement'!I37*B$13/(1+$A$14)^5 + 'DCF Valuation'!B31 + 'DCF Valuation'!B32) / 'DCF Valuation'!B37 -> 227.77896 | C14: =('DCF Valuation'!B26 + 'Income Statement'!I37*C$13/(1+$A$14)^5 + 'DCF Valuation'!B31 + 'DCF Valuation'!B32) / 'DCF Valuation'!B37 -> 252.53238 | D14: =('DCF Valuation'!B26 + 'Income Statement'!I37*D$13/(1+$A$14)^5 + 'DCF Valuation'!B31 + 'DCF Valuation'!B32) / 'DCF Valuation'!B37 -> 277.28579 | E14: =('DCF Valuation'!B26 + 'Income Statement'!I37*E$13/(1+$A$14)^5 + 'DCF Valuation'!B31 + 'DCF Valuation'!B32) / 'DCF Valuation'!B37 -> 302.03921 | F14: =('DCF Valuation'!B26 + 'Income Statement'!I37*F$13/(1+$A$14)^5 + 'DCF Valuation'!B31 + 'DCF Valuation'!B32) / 'DCF Valuation'!B37 -> 326.79262
A15: 0.09 | B15: =('DCF Valuation'!B26 + 'Income Statement'!I37*B$13/(1+$A$15)^5 + 'DCF Valuation'!B31 + 'DCF Valuation'!B32) / 'DCF Valuation'!B37 -> 218.8603 | C15: =('DCF Valuation'!B26 + 'Income Statement'!I37*C$13/(1+$A$15)^5 + 'DCF Valuation'!B31 + 'DCF Valuation'!B32) / 'DCF Valuation'!B37 -> 242.49888 | D15: =('DCF Valuation'!B26 + 'Income Statement'!I37*D$13/(1+$A$15)^5 + 'DCF Valuation'!B31 + 'DCF Valuation'!B32) / 'DCF Valuation'!B37 -> 266.13746 | E15: =('DCF Valuation'!B26 + 'Income Statement'!I37*E$13/(1+$A$15)^5 + 'DCF Valuation'!B31 + 'DCF Valuation'!B32) / 'DCF Valuation'!B37 -> 289.77604 | F15: =('DCF Valuation'!B26 + 'Income Statement'!I37*F$13/(1+$A$15)^5 + 'DCF Valuation'!B31 + 'DCF Valuation'!B32) / 'DCF Valuation'!B37 -> 313.41462
A16: 0.1 | B16: =('DCF Valuation'!B26 + 'Income Statement'!I37*B$13/(1+$A$16)^5 + 'DCF Valuation'!B31 + 'DCF Valuation'!B32) / 'DCF Valuation'!B37 -> 210.41932 | C16: =('DCF Valuation'!B26 + 'Income Statement'!I37*C$13/(1+$A$16)^5 + 'DCF Valuation'!B31 + 'DCF Valuation'!B32) / 'DCF Valuation'!B37 -> 233.00278 | D16: =('DCF Valuation'!B26 + 'Income Statement'!I37*D$13/(1+$A$16)^5 + 'DCF Valuation'!B31 + 'DCF Valuation'!B32) / 'DCF Valuation'!B37 -> 255.58624 | E16: =('DCF Valuation'!B26 + 'Income Statement'!I37*E$13/(1+$A$16)^5 + 'DCF Valuation'!B31 + 'DCF Valuation'!B32) / 'DCF Valuation'!B37 -> 278.1697 | F16: =('DCF Valuation'!B26 + 'Income Statement'!I37*F$13/(1+$A$16)^5 + 'DCF Valuation'!B31 + 'DCF Valuation'!B32) / 'DCF Valuation'!B37 -> 300.75316
A17: 0.11 | B17: =('DCF Valuation'!B26 + 'Income Statement'!I37*B$13/(1+$A$17)^5 + 'DCF Valuation'!B31 + 'DCF Valuation'!B32) / 'DCF Valuation'!B37 -> 202.42646 | C17: =('DCF Valuation'!B26 + 'Income Statement'!I37*C$13/(1+$A$17)^5 + 'DCF Valuation'!B31 + 'DCF Valuation'!B32) / 'DCF Valuation'!B37 -> 224.01081 | D17: =('DCF Valuation'!B26 + 'Income Statement'!I37*D$13/(1+$A$17)^5 + 'DCF Valuation'!B31 + 'DCF Valuation'!B32) / 'DCF Valuation'!B37 -> 245.59516 | E17: =('DCF Valuation'!B26 + 'Income Statement'!I37*E$13/(1+$A$17)^5 + 'DCF Valuation'!B31 + 'DCF Valuation'!B32) / 'DCF Valuation'!B37 -> 267.17951 | F17: =('DCF Valuation'!B26 + 'Income Statement'!I37*F$13/(1+$A$17)^5 + 'DCF Valuation'!B31 + 'DCF Valuation'!B32) / 'DCF Valuation'!B37 -> 288.76386
A18: 0.12 | B18: =('DCF Valuation'!B26 + 'Income Statement'!I37*B$13/(1+$A$18)^5 + 'DCF Valuation'!B31 + 'DCF Valuation'!B32) / 'DCF Valuation'!B37 -> 194.85419 | C18: =('DCF Valuation'!B26 + 'Income Statement'!I37*C$13/(1+$A$18)^5 + 'DCF Valuation'!B31 + 'DCF Valuation'!B32) / 'DCF Valuation'!B37 -> 215.49201 | D18: =('DCF Valuation'!B26 + 'Income Statement'!I37*D$13/(1+$A$18)^5 + 'DCF Valuation'!B31 + 'DCF Valuation'!B32) / 'DCF Valuation'!B37 -> 236.12983 | E18: =('DCF Valuation'!B26 + 'Income Statement'!I37*E$13/(1+$A$18)^5 + 'DCF Valuation'!B31 + 'DCF Valuation'!B32) / 'DCF Valuation'!B37 -> 256.76765 | F18: =('DCF Valuation'!B26 + 'Income Statement'!I37*F$13/(1+$A$18)^5 + 'DCF Valuation'!B31 + 'DCF Valuation'!B32) / 'DCF Valuation'!B37 -> 277.40547
