Workbook

Sheet Transaction
A1: Stanley Black & Decker (SWK) — LBO Transaction Summary | B1: Entry (FY2025) | C1: Year 1 | D1: Year 2 | E1: Year 3 | F1: Year 4 | G1: Year 5 / Exit
A3: Company Overview
A4: LTM Revenue ($mm) | B4: 15130 | H4: Source: SWK 10-K FY2025
A5: LTM EBITDA ($mm) | B5: 1600 | H5: Source: SWK 10-K FY2025 (adjusted)
A6: LTM EBITDA Margin | B6: =B5/B4 -> 0.10575017
A7: Current Share Price ($) | B7: 71
A8: Shares Outstanding (mm) | B8: 155
A9: Current Equity Value ($mm) | B9: =B7*B8 -> 11005
A10: Existing Debt ($mm) | B10: 5500 | H10: Source: SWK 10-K, midpoint of $5.3-5.86B range
A11: Cash on Hand ($mm) | B11: 300 | H11: Source: SWK 10-K FY2025 estimate
A12: Current Enterprise Value ($mm) | B12: =B9+B10-B11 -> 16205
A13: Current EV / EBITDA | B13: =B12/B5 -> 10.128125
A15: Acquisition Assumptions
A16: Acquisition Premium | B16: 0.15 | H16: Key assumption — 15% premium to unaffected price
A17: Offer Price per Share ($) | B17: =B7*(1+B16) -> 81.65
A18: Equity Purchase Price ($mm) | B18: =B17*B8 -> 12655.75
A19: Transaction Fees ($mm) | B19: 150 | H19: ~1% of EV, banker/legal/advisory
A20: Total Enterprise Value ($mm) | B20: =B18+B10-B11+B19 -> 18005.75
A21: Implied Entry Multiple (EV/EBITDA) | B21: =B20/B5 -> 11.253594
A23: Capital Structure — Sources & Uses
A24: SOURCES | B24: Amount ($mm) | C24: Multiple | D24: Rate
A25: Senior Secured Term Loan | B25: =B5*3.5 -> 5600 | C25: 3.5 | D25: 0.065
A26: High-Yield Unsecured Notes | B26: =B5*2 -> 3200 | C26: 2 | D26: 0.09
A27: Total Debt | B27: =B25+B26 -> 8800 | C27: =B27/B5 -> 5.5
A28: Sponsor Equity | B28: =B20-B27 -> 9205.75
A29: Total Sources | B29: =B27+B28 -> 18005.75
A31: USES | B31: Amount ($mm)
A32: Equity Purchase Price | B32: =B18 -> 12655.75
A33: Refinance Existing Debt | B33: =B10 -> 5500
A34: Transaction Fees | B34: =B19 -> 150
A35: Less: Cash on Hand | B35: =-B11 -> -300
A36: Total Uses | B36: =B32+B33+B34+B35 -> 18005.75
A38: Sources - Uses Check | B38: =B29-B36 -> 0

Sheet Operating Model
A1: SWK — Operating Model ($mm) | B1: Entry (FY2025) | C1: Year 1 | D1: Year 2 | E1: Year 3 | F1: Year 4 | G1: Year 5 / Exit
A3: Revenue Build
A4: Revenue Growth Rate | C4: 0.03 | D4: 0.03 | E4: 0.03 | F4: 0.03 | G4: 0.03
A5: Total Revenue | B5: =Transaction!B4 -> 15130 | C5: =B5*(1+C4) -> 15583.9 | D5: =C5*(1+D4) -> 16051.417 | E5: =D5*(1+E4) -> 16532.96 | F5: =E5*(1+F4) -> 17028.948 | G5: =F5*(1+G4) -> 17539.817
A7: EBITDA Build
A8: EBITDA Margin | B8: 0.106 | C8: 0.125 | D8: 0.14 | E8: 0.15 | F8: 0.16 | G8: 0.17
A9: EBITDA | B9: =B5*B8 -> 1603.78 | C9: =C5*C8 -> 1947.9875 | D9: =D5*D8 -> 2247.1984 | E9: =E5*E8 -> 2479.9439 | F9: =F5*F8 -> 2724.6317 | G9: =G5*G8 -> 2981.7688
A10: EBITDA Growth % | C10: =(C9-B9)/B9 -> 0.21462264 | D10: =(D9-C9)/C9 -> 0.1536 | E10: =(E9-D9)/D9 -> 0.10357143 | F10: =(F9-E9)/E9 -> 0.098666667 | G10: =(G9-F9)/F9 -> 0.094375
A12: Free Cash Flow
A13: EBITDA | B13: =B9 -> 1603.78 | C13: =C9 -> 1947.9875 | D13: =D9 -> 2247.1984 | E13: =E9 -> 2479.9439 | F13: =F9 -> 2724.6317 | G13: =G9 -> 2981.7688
A14: (-) D&A | B14: -500 | C14: =B14*1.02 -> -510 | D14: =C14*1.02 -> -520.2 | E14: =D14*1.02 -> -530.604 | F14: =E14*1.02 -> -541.21608 | G14: =F14*1.02 -> -552.0404
A15: EBIT | B15: =B13+B14 -> 1103.78 | C15: =C13+C14 -> 1437.9875 | D15: =D13+D14 -> 1726.9984 | E15: =E13+E14 -> 1949.3399 | F15: =F13+F14 -> 2183.4156 | G15: =G13+G14 -> 2429.7284
A16: (-) Cash Taxes @ 25% | B16: =-B15*0.25 -> -275.945 | C16: =-C15*0.25 -> -359.49687 | D16: =-D15*0.25 -> -431.74959 | E16: =-E15*0.25 -> -487.33498 | F16: =-F15*0.25 -> -545.85391 | G16: =-G15*0.25 -> -607.43211
A17: (+) D&A Add-Back | B17: =-B14 -> 500 | C17: =-C14 -> 510 | D17: =-D14 -> 520.2 | E17: =-E14 -> 530.604 | F17: =-F14 -> 541.21608 | G17: =-G14 -> 552.0404
A18: (-) CapEx (% of Revenue) | B18: =-B5*0.025 -> -378.25 | C18: =-C5*0.025 -> -389.5975 | D18: =-D5*0.025 -> -401.28542 | E18: =-E5*0.025 -> -413.32399 | F18: =-F5*0.025 -> -425.72371 | G18: =-G5*0.025 -> -438.49542
A19: (-) Change in NWC | B19: 0 | C19: 0 | D19: 0 | E19: 0 | F19: 0 | G19: 0
A21: Levered Free Cash Flow | B21: =B15+B16+B17+B18+B19 -> 949.585 | C21: =C15+C16+C17+C18+C19 -> 1198.8931 | D21: =D15+D16+D17+D18+D19 -> 1414.1634 | E21: =E15+E16+E17+E18+E19 -> 1579.285 | F21: =F15+F16+F17+F18+F19 -> 1753.0541 | G21: =G15+G16+G17+G18+G19 -> 1935.8413
A23: Interest Expense
A24: Interest on Senior Debt | B24: ='Debt Schedule'!B4*Transaction!$D$25 -> 364 | C24: ='Debt Schedule'!C4*Transaction!$D$25 -> 356.72 | D24: ='Debt Schedule'!D4*Transaction!$D$25 -> 349.44 | E24: ='Debt Schedule'!E4*Transaction!$D$25 -> 342.16 | F24: ='Debt Schedule'!F4*Transaction!$D$25 -> 334.88 | G24: ='Debt Schedule'!G4*Transaction!$D$25 -> 327.6
A25: Interest on HY Notes | B25: ='Debt Schedule'!B10*Transaction!$D$26 -> 288 | C25: ='Debt Schedule'!C10*Transaction!$D$26 -> 271.29735 | D25: ='Debt Schedule'!D10*Transaction!$D$26 -> 229.99853 | E25: ='Debt Schedule'!E10*Transaction!$D$26 -> 164.9533 | F25: ='Debt Schedule'!F10*Transaction!$D$26 -> 78.537846 | G25: ='Debt Schedule'!G10*Transaction!$D$26 -> 0
A26: Total Interest Expense | B26: =B24+B25 -> 652 | C26: =C24+C25 -> 628.01735 | D26: =D24+D25 -> 579.43853 | E26: =E24+E25 -> 507.1133 | F26: =F24+F25 -> 413.41785 | G26: =G24+G25 -> 327.6
A28: FCF Available for Debt Repayment | B28: =B21-B26 -> 297.585 | C28: =C21-C26 -> 570.87577 | D28: =D21-D26 -> 834.72483 | E28: =E21-E26 -> 1072.1717 | F28: =F21-F26 -> 1339.6363 | G28: =G21-G26 -> 1608.2413

Sheet Debt Schedule
A1: SWK — Debt Schedule ($mm) | B1: Entry (FY2025) | C1: Year 1 | D1: Year 2 | E1: Year 3 | F1: Year 4 | G1: Year 5 / Exit
A3: Senior Secured Term Loan (3.5x)
A4: Beginning Balance | B4: =Transaction!B25 -> 5600 | C4: =B6 -> 5488 | D4: =C6 -> 5376 | E4: =D6 -> 5264 | F4: =E6 -> 5152 | G4: =F6 -> 5040
A5: (-) Mandatory Amortization (2%/yr) | B5: =-Transaction!$B$25*0.02 -> -112 | C5: =-Transaction!$B$25*0.02 -> -112 | D5: =-Transaction!$B$25*0.02 -> -112 | E5: =-Transaction!$B$25*0.02 -> -112 | F5: =-Transaction!$B$25*0.02 -> -112 | G5: =-Transaction!$B$25*0.02 -> -112
A6: Ending Balance | B6: =MAX(0,B4+B5) -> 5488 | C6: =MAX(0,C4+C5) -> 5376 | D6: =MAX(0,D4+D5) -> 5264 | E6: =MAX(0,E4+E5) -> 5152 | F6: =MAX(0,F4+F5) -> 5040 | G6: =MAX(0,G4+G5) -> 4928
A7: Senior Leverage (x EBITDA) | B7: =B6/'Operating Model'!B9 -> 3.4219157 | C7: =C6/'Operating Model'!C9 -> 2.7597713 | D7: =D6/'Operating Model'!D9 -> 2.3424723 | E7: =E6/'Operating Model'!E9 -> 2.0774663 | F7: =F6/'Operating Model'!F9 -> 1.8497913 | G7: =G6/'Operating Model'!G9 -> 1.6527103
A9: High-Yield Unsecured Notes (2.0x)
A10: Beginning Balance | B10: =Transaction!B26 -> 3200 | C10: =B12 -> 3014.415 | D10: =C12 -> 2555.5392 | E10: =D12 -> 1832.8144 | F10: =E12 -> 872.64273 | G10: =F12 -> 0
A11: Repayment (from excess FCF) | B11: =-MIN(B10, MAX(0, 'Operating Model'!B28+B5)) -> -185.585 | C11: =-MIN(C10, MAX(0, 'Operating Model'!C28+C5)) -> -458.87577 | D11: =-MIN(D10, MAX(0, 'Operating Model'!D28+D5)) -> -722.72483 | E11: =-MIN(E10, MAX(0, 'Operating Model'!E28+E5)) -> -960.17166 | F11: =-MIN(F10, MAX(0, 'Operating Model'!F28+F5)) -> -872.64273 | G11: =-MIN(G10, MAX(0, 'Operating Model'!G28+G5)) -> 0
A12: Ending Balance | B12: =MAX(0,B10+B11) -> 3014.415 | C12: =MAX(0,C10+C11) -> 2555.5392 | D12: =MAX(0,D10+D11) -> 1832.8144 | E12: =MAX(0,E10+E11) -> 872.64273 | F12: =MAX(0,F10+F11) -> 0 | G12: =MAX(0,G10+G11) -> 0
A14: Total Debt Summary
A15: Total Debt | B15: =B6+B12 -> 8502.415 | C15: =C6+C12 -> 7931.5392 | D15: =D6+D12 -> 7096.8144 | E15: =E6+E12 -> 6024.6427 | F15: =F6+F12 -> 5040 | G15: =G6+G12 -> 4928
A16: Total Leverage (x EBITDA) | B16: =B15/'Operating Model'!B9 -> 5.3014846 | C16: =C15/'Operating Model'!C9 -> 4.0716582 | D16: =D15/'Operating Model'!D9 -> 3.1580721 | E16: =E15/'Operating Model'!E9 -> 2.4293464 | F16: =F15/'Operating Model'!F9 -> 1.8497913 | G16: =G15/'Operating Model'!G9 -> 1.6527103
A17: Cumulative Debt Repaid | B17: 0 | C17: =Transaction!B27-C15 -> 868.46078 | D17: =Transaction!B27-D15 -> 1703.1856 | E17: =Transaction!B27-E15 -> 2775.3573 | F17: =Transaction!B27-F15 -> 3760 | G17: =Transaction!B27-G15 -> 3872

Sheet Returns
A1: SWK — Returns Analysis | B1: Entry (FY2025) | C1: Year 1 | D1: Year 2 | E1: Year 3 | F1: Year 4 | G1: Year 5 / Exit
A3: Equity Value Buildup
A4: EBITDA | B4: ='Operating Model'!B9 -> 1603.78 | C4: ='Operating Model'!C9 -> 1947.9875 | D4: ='Operating Model'!D9 -> 2247.1984 | E4: ='Operating Model'!E9 -> 2479.9439 | F4: ='Operating Model'!F9 -> 2724.6317 | G4: ='Operating Model'!G9 -> 2981.7688
A5: Exit Multiple | B5: =Transaction!B21 -> 11.253594 | C5: 13 | D5: 13 | E5: 13 | F5: 13 | G5: 13
A6: Implied Enterprise Value | B6: =B4*B5 -> 18048.289 | C6: =C4*C5 -> 25323.838 | D6: =D4*D5 -> 29213.579 | E6: =E4*E5 -> 32239.271 | F6: =F4*F5 -> 35420.212 | G6: =G4*G5 -> 38762.995
A7: (-) Total Debt | B7: =-'Debt Schedule'!B15 -> -8502.415 | C7: =-'Debt Schedule'!C15 -> -7931.5392 | D7: =-'Debt Schedule'!D15 -> -7096.8144 | E7: =-'Debt Schedule'!E15 -> -6024.6427 | F7: =-'Debt Schedule'!F15 -> -5040 | G7: =-'Debt Schedule'!G15 -> -4928
A8: Implied Equity Value | B8: =B6+B7 -> 9545.8736 | C8: =C6+C7 -> 17392.298 | D8: =D6+D7 -> 22116.765 | E8: =E6+E7 -> 26214.628 | F8: =F6+F7 -> 30380.212 | G8: =G6+G7 -> 33834.995
A10: Sponsor Returns (if exited at each year)
A11: Sponsor Equity Invested | B11: =Transaction!B28 -> 9205.75 | C11: =Transaction!B28 -> 9205.75 | D11: =Transaction!B28 -> 9205.75 | E11: =Transaction!B28 -> 9205.75 | F11: =Transaction!B28 -> 9205.75 | G11: =Transaction!B28 -> 9205.75
A12: MOIC | B12: =B8/B11 -> 1.0369469 | C12: =C8/C11 -> 1.8892864 | D12: =D8/D11 -> 2.4024946 | E12: =E8/E11 -> 2.8476363 | F12: =F8/F11 -> 3.3001344 | G12: =G8/G11 -> 3.6754197
A13: IRR | C13: =IFERROR((C8/C11)^(1/1)-1,0) -> 0.8892864 | D13: =IFERROR((D8/D11)^(1/2)-1,0) -> 0.54999825 | E13: =IFERROR((E8/E11)^(1/3)-1,0) -> 0.41740788 | F13: =IFERROR((F8/F11)^(1/4)-1,0) -> 0.34782314 | G13: =IFERROR((G8/G11)^(1/5)-1,0) -> 0.29736264
A15: Return Attribution (Year 5 Exit)
A16: Entry Enterprise Value | B16: =Transaction!B20 -> 18005.75
A17: Exit Enterprise Value | B17: =G6 -> 38762.995
A18: Total EV Gain | B18: =B17-B16 -> 20757.245
A19: From EBITDA Growth | B19: =(G4-Transaction!B5)*B5 -> 15549.865
A20: From Multiple Expansion | B20: =B18-B19 -> 5207.3797
A21: Total Debt Repaid Over Hold | B21: =Transaction!B27-'Debt Schedule'!G15 -> 3872
A23: 5-Year MOIC | B23: =G12 -> 3.6754197
A24: 5-Year IRR | B24: =G13 -> 0.29736264

Sheet Sensitivity
A1: SWK — IRR Sensitivity Analysis
A3: IRR: Exit Multiple vs EBITDA Margin at Exit
A4: Exit Mult ↓ / Margin → | B4: 0.15 | C4: 0.16 | D4: 0.17 | E4: 0.18 | F4: 0.19
A5: 11 | B5: =IFERROR(((Transaction!B4*(1.03)^5*B$4*$A$5-'Debt Schedule'!G15)/Transaction!B28)^(1/5)-1,0) -> 0.21136872 | C5: =IFERROR(((Transaction!B4*(1.03)^5*C$4*$A$5-'Debt Schedule'!G15)/Transaction!B28)^(1/5)-1,0) -> 0.23023794 | D5: =IFERROR(((Transaction!B4*(1.03)^5*D$4*$A$5-'Debt Schedule'!G15)/Transaction!B28)^(1/5)-1,0) -> 0.24801585 | E5: =IFERROR(((Transaction!B4*(1.03)^5*E$4*$A$5-'Debt Schedule'!G15)/Transaction!B28)^(1/5)-1,0) -> 0.26483495 | F5: =IFERROR(((Transaction!B4*(1.03)^5*F$4*$A$5-'Debt Schedule'!G15)/Transaction!B28)^(1/5)-1,0) -> 0.28080429
A6: 12 | B6: =IFERROR(((Transaction!B4*(1.03)^5*B$4*$A$6-'Debt Schedule'!G15)/Transaction!B28)^(1/5)-1,0) -> 0.23682135 | C6: =IFERROR(((Transaction!B4*(1.03)^5*C$4*$A$6-'Debt Schedule'!G15)/Transaction!B28)^(1/5)-1,0) -> 0.25577272 | D6: =IFERROR(((Transaction!B4*(1.03)^5*D$4*$A$6-'Debt Schedule'!G15)/Transaction!B28)^(1/5)-1,0) -> 0.27364467 | E6: =IFERROR(((Transaction!B4*(1.03)^5*E$4*$A$6-'Debt Schedule'!G15)/Transaction!B28)^(1/5)-1,0) -> 0.29056637 | F6: =IFERROR(((Transaction!B4*(1.03)^5*F$4*$A$6-'Debt Schedule'!G15)/Transaction!B28)^(1/5)-1,0) -> 0.30664448
A7: 13 | B7: =IFERROR(((Transaction!B4*(1.03)^5*B$4*$A$7-'Debt Schedule'!G15)/Transaction!B28)^(1/5)-1,0) -> 0.26033642 | C7: =IFERROR(((Transaction!B4*(1.03)^5*C$4*$A$7-'Debt Schedule'!G15)/Transaction!B28)^(1/5)-1,0) -> 0.27938514 | D7: =IFERROR(((Transaction!B4*(1.03)^5*D$4*$A$7-'Debt Schedule'!G15)/Transaction!B28)^(1/5)-1,0) -> 0.29736264 | E7: =IFERROR(((Transaction!B4*(1.03)^5*E$4*$A$7-'Debt Schedule'!G15)/Transaction!B28)^(1/5)-1,0) -> 0.31439561 | F7: =IFERROR(((Transaction!B4*(1.03)^5*F$4*$A$7-'Debt Schedule'!G15)/Transaction!B28)^(1/5)-1,0) -> 0.33058887
A8: 14 | B8: =IFERROR(((Transaction!B4*(1.03)^5*B$4*$A$8-'Debt Schedule'!G15)/Transaction!B28)^(1/5)-1,0) -> 0.28221717 | C8: =IFERROR(((Transaction!B4*(1.03)^5*C$4*$A$8-'Debt Schedule'!G15)/Transaction!B28)^(1/5)-1,0) -> 0.30137303 | D8: =IFERROR(((Transaction!B4*(1.03)^5*D$4*$A$8-'Debt Schedule'!G15)/Transaction!B28)^(1/5)-1,0) -> 0.31946321 | E8: =IFERROR(((Transaction!B4*(1.03)^5*E$4*$A$8-'Debt Schedule'!G15)/Transaction!B28)^(1/5)-1,0) -> 0.33661249 | F8: =IFERROR(((Transaction!B4*(1.03)^5*F$4*$A$8-'Debt Schedule'!G15)/Transaction!B28)^(1/5)-1,0) -> 0.3529243
A9: 15 | B9: =IFERROR(((Transaction!B4*(1.03)^5*B$4*$A$9-'Debt Schedule'!G15)/Transaction!B28)^(1/5)-1,0) -> 0.30269891 | C9: =IFERROR(((Transaction!B4*(1.03)^5*C$4*$A$9-'Debt Schedule'!G15)/Transaction!B28)^(1/5)-1,0) -> 0.3219681 | D9: =IFERROR(((Transaction!B4*(1.03)^5*D$4*$A$9-'Debt Schedule'!G15)/Transaction!B28)^(1/5)-1,0) -> 0.3401752 | E9: =IFERROR(((Transaction!B4*(1.03)^5*E$4*$A$9-'Debt Schedule'!G15)/Transaction!B28)^(1/5)-1,0) -> 0.35744349 | F9: =IFERROR(((Transaction!B4*(1.03)^5*F$4*$A$9-'Debt Schedule'!G15)/Transaction!B28)^(1/5)-1,0) -> 0.37387532
A12: IRR: Entry Premium vs Exit Multiple
A13: Premium ↓ / Exit Mult → | B13: 11 | C13: 12 | D13: 13 | E13: 14 | F13: 15
A14: 0.1 | B14: =IFERROR(((Transaction!B4*(1.03)^5*0.17*B$13-'Debt Schedule'!G15)/(Transaction!B7*(1+$A$14)*Transaction!B8+Transaction!B10-Transaction!B11+Transaction!B19-Transaction!B27))^(1/5)-1,0) -> 0.26349493 | C14: =IFERROR(((Transaction!B4*(1.03)^5*0.17*C$13-'Debt Schedule'!G15)/(Transaction!B7*(1+$A$14)*Transaction!B8+Transaction!B10-Transaction!B11+Transaction!B19-Transaction!B27))^(1/5)-1,0) -> 0.28944162 | D14: =IFERROR(((Transaction!B4*(1.03)^5*0.17*D$13-'Debt Schedule'!G15)/(Transaction!B7*(1+$A$14)*Transaction!B8+Transaction!B10-Transaction!B11+Transaction!B19-Transaction!B27))^(1/5)-1,0) -> 0.31345377 | E14: =IFERROR(((Transaction!B4*(1.03)^5*0.17*E$13-'Debt Schedule'!G15)/(Transaction!B7*(1+$A$14)*Transaction!B8+Transaction!B10-Transaction!B11+Transaction!B19-Transaction!B27))^(1/5)-1,0) -> 0.33582845 | F14: =IFERROR(((Transaction!B4*(1.03)^5*0.17*F$13-'Debt Schedule'!G15)/(Transaction!B7*(1+$A$14)*Transaction!B8+Transaction!B10-Transaction!B11+Transaction!B19-Transaction!B27))^(1/5)-1,0) -> 0.35679733
A15: 0.15 | B15: =IFERROR(((Transaction!B4*(1.03)^5*0.17*B$13-'Debt Schedule'!G15)/(Transaction!B7*(1+$A$15)*Transaction!B8+Transaction!B10-Transaction!B11+Transaction!B19-Transaction!B27))^(1/5)-1,0) -> 0.24801585 | C15: =IFERROR(((Transaction!B4*(1.03)^5*0.17*C$13-'Debt Schedule'!G15)/(Transaction!B7*(1+$A$15)*Transaction!B8+Transaction!B10-Transaction!B11+Transaction!B19-Transaction!B27))^(1/5)-1,0) -> 0.27364467 | D15: =IFERROR(((Transaction!B4*(1.03)^5*0.17*D$13-'Debt Schedule'!G15)/(Transaction!B7*(1+$A$15)*Transaction!B8+Transaction!B10-Transaction!B11+Transaction!B19-Transaction!B27))^(1/5)-1,0) -> 0.29736264 | E15: =IFERROR(((Transaction!B4*(1.03)^5*0.17*E$13-'Debt Schedule'!G15)/(Transaction!B7*(1+$A$15)*Transaction!B8+Transaction!B10-Transaction!B11+Transaction!B19-Transaction!B27))^(1/5)-1,0) -> 0.31946321 | F15: =IFERROR(((Transaction!B4*(1.03)^5*0.17*F$13-'Debt Schedule'!G15)/(Transaction!B7*(1+$A$15)*Transaction!B8+Transaction!B10-Transaction!B11+Transaction!B19-Transaction!B27))^(1/5)-1,0) -> 0.3401752
A16: 0.2 | B16: =IFERROR(((Transaction!B4*(1.03)^5*0.17*B$13-'Debt Schedule'!G15)/(Transaction!B7*(1+$A$16)*Transaction!B8+Transaction!B10-Transaction!B11+Transaction!B19-Transaction!B27))^(1/5)-1,0) -> 0.23360914 | C16: =IFERROR(((Transaction!B4*(1.03)^5*0.17*C$13-'Debt Schedule'!G15)/(Transaction!B7*(1+$A$16)*Transaction!B8+Transaction!B10-Transaction!B11+Transaction!B19-Transaction!B27))^(1/5)-1,0) -> 0.2589421 | D16: =IFERROR(((Transaction!B4*(1.03)^5*0.17*D$13-'Debt Schedule'!G15)/(Transaction!B7*(1+$A$16)*Transaction!B8+Transaction!B10-Transaction!B11+Transaction!B19-Transaction!B27))^(1/5)-1,0) -> 0.28238629 | E16: =IFERROR(((Transaction!B4*(1.03)^5*0.17*E$13-'Debt Schedule'!G15)/(Transaction!B7*(1+$A$16)*Transaction!B8+Transaction!B10-Transaction!B11+Transaction!B19-Transaction!B27))^(1/5)-1,0) -> 0.30423174 | F16: =IFERROR(((Transaction!B4*(1.03)^5*0.17*F$13-'Debt Schedule'!G15)/(Transaction!B7*(1+$A$16)*Transaction!B8+Transaction!B10-Transaction!B11+Transaction!B19-Transaction!B27))^(1/5)-1,0) -> 0.32470463
A17: 0.25 | B17: =IFERROR(((Transaction!B4*(1.03)^5*0.17*B$13-'Debt Schedule'!G15)/(Transaction!B7*(1+$A$17)*Transaction!B8+Transaction!B10-Transaction!B11+Transaction!B19-Transaction!B27))^(1/5)-1,0) -> 0.220146 | C17: =IFERROR(((Transaction!B4*(1.03)^5*0.17*C$13-'Debt Schedule'!G15)/(Transaction!B7*(1+$A$17)*Transaction!B8+Transaction!B10-Transaction!B11+Transaction!B19-Transaction!B27))^(1/5)-1,0) -> 0.24520249 | D17: =IFERROR(((Transaction!B4*(1.03)^5*0.17*D$13-'Debt Schedule'!G15)/(Transaction!B7*(1+$A$17)*Transaction!B8+Transaction!B10-Transaction!B11+Transaction!B19-Transaction!B27))^(1/5)-1,0) -> 0.26839082 | E17: =IFERROR(((Transaction!B4*(1.03)^5*0.17*E$13-'Debt Schedule'!G15)/(Transaction!B7*(1+$A$17)*Transaction!B8+Transaction!B10-Transaction!B11+Transaction!B19-Transaction!B27))^(1/5)-1,0) -> 0.28999785 | F17: =IFERROR(((Transaction!B4*(1.03)^5*0.17*F$13-'Debt Schedule'!G15)/(Transaction!B7*(1+$A$17)*Transaction!B8+Transaction!B10-Transaction!B11+Transaction!B19-Transaction!B27))^(1/5)-1,0) -> 0.31024731
A18: 0.3 | B18: =IFERROR(((Transaction!B4*(1.03)^5*0.17*B$13-'Debt Schedule'!G15)/(Transaction!B7*(1+$A$18)*Transaction!B8+Transaction!B10-Transaction!B11+Transaction!B19-Transaction!B27))^(1/5)-1,0) -> 0.20751899 | C18: =IFERROR(((Transaction!B4*(1.03)^5*0.17*C$13-'Debt Schedule'!G15)/(Transaction!B7*(1+$A$18)*Transaction!B8+Transaction!B10-Transaction!B11+Transaction!B19-Transaction!B27))^(1/5)-1,0) -> 0.23231618 | D18: =IFERROR(((Transaction!B4*(1.03)^5*0.17*D$13-'Debt Schedule'!G15)/(Transaction!B7*(1+$A$18)*Transaction!B8+Transaction!B10-Transaction!B11+Transaction!B19-Transaction!B27))^(1/5)-1,0) -> 0.25526453 | E18: =IFERROR(((Transaction!B4*(1.03)^5*0.17*E$13-'Debt Schedule'!G15)/(Transaction!B7*(1+$A$18)*Transaction!B8+Transaction!B10-Transaction!B11+Transaction!B19-Transaction!B27))^(1/5)-1,0) -> 0.27664796 | F18: =IFERROR(((Transaction!B4*(1.03)^5*0.17*F$13-'Debt Schedule'!G15)/(Transaction!B7*(1+$A$18)*Transaction!B8+Transaction!B10-Transaction!B11+Transaction!B19-Transaction!B27))^(1/5)-1,0) -> 0.29668786
